.DS_Store
django_cli/__init__.py
django_cli/create_new_project.py
django_cli_big2tinydev-0.0.4.dist-info/LICENSE
django_cli_big2tinydev-0.0.4.dist-info/METADATA
django_cli_big2tinydev-0.0.4.dist-info/WHEEL
django_cli_big2tinydev-0.0.4.dist-info/entry_points.txt
django_cli_big2tinydev-0.0.4.dist-info/top_level.txt
django_cli_big2tinydev-0.0.4.dist-info/RECORD
